{
  "task_id": "triage-single-bug",
  "difficulty": "medium",
  "category": "issues",
  "instructions": "There's a production bug reported in the repo. Review it, triage it appropriately with severity and category labels, assign it to the right person, and leave a triage comment explaining the impact. Check the available labels and use your judgment on severity.",
  "max_steps": 10,
  "seed": {
    "repos": [
      {"id": 1, "name": "backend", "description": "Backend API service", "default_branch": "main"}
    ],
    "branches": [
      {"id": 1, "repo_id": 1, "name": "main", "base_branch": "main"}
    ],
    "files": [
      {"id": 1, "branch_id": 1, "path": "src/app.py", "content": "from flask import Flask\napp = Flask(__name__)\n"}
    ],
    "labels": [
      {"id": 1, "repo_id": 1, "name": "bug", "color": "d73a4a"},
      {"id": 2, "repo_id": 1, "name": "critical", "color": "b60205"},
      {"id": 3, "repo_id": 1, "name": "enhancement", "color": "a2eeef"}
    ],
    "issues": [
      {"id": 1, "repo_id": 1, "number": 1, "title": "Null pointer in user service", "body": "The /api/users/:id endpoint throws a NullPointerException when the user profile has no email set. This is affecting ~5% of production requests.", "status": "open"}
    ],
    "issue_labels": [],
    "issue_comments": [],
    "pull_requests": [],
    "pr_reviews": [],
    "pr_comments": [],
    "projects": [],
    "project_items": [],
    "commits": [],
    "pr_linked_issues": []
  },
  "eval_criteria": [
    {
      "description": "Issue #1 has 'bug' label",
      "table": "issue_labels",
      "check": "exists",
      "params": {"issue_id": 1, "label_id": 1},
      "weight": 0.25
    },
    {
      "description": "Issue #1 has 'critical' label",
      "table": "issue_labels",
      "check": "exists",
      "params": {"issue_id": 1, "label_id": 2},
      "weight": 0.25
    },
    {
      "description": "Issue #1 assigned to alice",
      "table": "issues",
      "check": "field_equals",
      "params": {"where": {"number": 1, "repo_id": 1}, "field": "assignee", "value": "alice"},
      "weight": 0.25
    },
    {
      "description": "Issue #1 has a triage comment mentioning production or P0",
      "table": "issue_comments",
      "check": "field_contains",
      "params": {"where": {"issue_id": 1}, "field": "body", "substring": "production"},
      "weight": 0.25
    }
  ]
}
